LICENSE
LICENSE_cctorch
README.md
pyproject.toml
setup.py
sam2/__init__.py
sam2/automatic_mask_generator.py
sam2/build_sam.py
sam2/sam2_image_predictor.py
sam2/sam2_video_predictor.py
sam2.egg-info/PKG-INFO
sam2.egg-info/SOURCES.txt
sam2.egg-info/dependency_links.txt
sam2.egg-info/requires.txt
sam2.egg-info/top_level.txt
sam2/csrc/connected_components.cu
sam2/modeling/__init__.py
sam2/modeling/memory_attention.py
sam2/modeling/memory_encoder.py
sam2/modeling/position_encoding.py
sam2/modeling/sam2_base.py
sam2/modeling/sam2_utils.py
sam2/modeling/backbones/__init__.py
sam2/modeling/backbones/hieradet.py
sam2/modeling/backbones/image_encoder.py
sam2/modeling/backbones/utils.py
sam2/modeling/sam/__init__.py
sam2/modeling/sam/mask_decoder.py
sam2/modeling/sam/prompt_encoder.py
sam2/modeling/sam/transformer.py
sam2/utils/__init__.py
sam2/utils/amg.py
sam2/utils/misc.py
sam2/utils/transforms.py
sam2_configs/__init__.py
sam2_configs/sam2_hiera_b+.yaml
sam2_configs/sam2_hiera_l.yaml
sam2_configs/sam2_hiera_s.yaml
sam2_configs/sam2_hiera_t.yaml