Metadata-Version: 2.1
Name: sam2
Version: 1.2.0
Summary: SAM 2: Segment Anything in Images and Videos
Home-page: https://github.com/facebookresearch/segment-anything-2
Author: Meta AI
Author-email: segment-anything@meta.com
License: Apache 2.0
Platform: UNKNOWN
Requires-Python: >=3.10.0
Provides-Extra: demo
Provides-Extra: dev
License-File: LICENSE
License-File: LICENSE_cctorch
